cds_302_project/__init__.py
cds_302_project/config.py
cds_302_project/data/cds302.db
cds_302_project/data/food_data.xlsx
cds_302_project/data_handler.py
cds_302_project/db.py
cds_302_project/main.py
cds_302_project/output/logs/data_handler.log
cds_302_project-0.1.0.dist-info/METADATA
cds_302_project-0.1.0.dist-info/WHEEL
cds_302_project-0.1.0.dist-info/RECORD
